pubtator_loader/__init__.py
pubtator_loader/__version__.py
pubtator_loader/pubtator_corpus_reader.py
pubtator_loader/models/__init__.py
pubtator_loader/models/pubtator_document.py
pubtator_loader/models/pubtator_entities.py
pubtator_loader-0.1.4.dist-info/LICENSE
pubtator_loader-0.1.4.dist-info/METADATA
pubtator_loader-0.1.4.dist-info/WHEEL
pubtator_loader-0.1.4.dist-info/top_level.txt
pubtator_loader-0.1.4.dist-info/zip-safe
pubtator_loader-0.1.4.dist-info/RECORD
