Metadata-Version: 2.1
Name: pubtator-loader
Version: 0.1.4
Summary: Parse PubTator files with ease
Home-page: https://github.com/arshsekhon/pubtator_loader
Author: Arsh Sekhon
Author-email: arshs3khon@gmail.com
License: GNU GPL v3
Platform: UNKNOWN
Classifier: Programming Language :: Python :: 3
Classifier: Operating System :: OS Independent
Requires-Dist: spacy (==3.0.5)
